rhizopus/__init__.py
rhizopus/broker.py
rhizopus/broker_observer.py
rhizopus/broker_simulator.py
rhizopus/enums.py
rhizopus/orders.py
rhizopus/price_graph.py
rhizopus/primitives.py
rhizopus/series_recorder.py
rhizopus/strategy.py
rhizopus/types.py
rhizopus-0.0.10.dist-info/LICENSE
rhizopus-0.0.10.dist-info/METADATA
rhizopus-0.0.10.dist-info/WHEEL
rhizopus-0.0.10.dist-info/top_level.txt
rhizopus-0.0.10.dist-info/RECORD
