Metadata-Version: 2.1
Name: rhizopus
Version: 0.0.10
Summary: Trading simulation framework
Home-page: https://github.com/jwergieluk/rhizopus
Author: Julian Wergieluk
Author-email: julian@wergieluk.com
License: UNKNOWN
Platform: UNKNOWN
Classifier: Programming Language :: Python :: 3
Classifier: License :: OSI Approved :: GNU General Public License v3 (GPLv3)
Classifier: Operating System :: OS Independent
License-File: LICENSE
